setup.py
aa_utility_package.egg-info/PKG-INFO
aa_utility_package.egg-info/SOURCES.txt
aa_utility_package.egg-info/dependency_links.txt
aa_utility_package.egg-info/not-zip-safe
aa_utility_package.egg-info/top_level.txt
aautilitypkg/__init__.py