Metadata-Version: 1.0
Name: aa-utility-package
Version: 0.1
Summary: Utility functions
Home-page: UNKNOWN
Author: Gaurav Sharma
Author-email: gauravdbdev@gmail.com
License: MIT
Platform: UNKNOWN
